Metadata-Version: 2.1
Name: oreoRS
Version: 0.3
Summary: Giting info for any account in the instagram account
Author: oreoRS
Author-email: zyaahee@gmail.com
Classifier: Programming Language :: Python :: 3
Classifier: Operating System :: OS Independent
Classifier: License :: OSI Approved :: MIT License
